navsim_envs/__init__.py
navsim_envs/env_kill.py
navsim_envs/env_tst.py
navsim_envs/version.txt
navsim_envs/benchmarks/__init__.py
navsim_envs/benchmarks/benchmark.py
navsim_envs/benchmarks/saturate_gpu.py
navsim_envs/env/__init__.py
navsim_envs/env/arora_gym_env.py
navsim_envs/env/arora_unity_env.py
navsim_envs/env/map_side_channel.py
navsim_envs/env/navigable_side_channel.py
navsim_envs/env/set_agent_position_side_channel.py
navsim_envs/test/__init__.py
navsim_envs/test/conftest.py
navsim_envs/test/navsim_gym_env_test.py
navsim_envs/util/__init__.py
navsim_envs/util/configs.py
navsim_envs/util/env_utils.py
navsim_envs/util/exceptions.py
navsim_envs-2.10.9.dist-info/METADATA
navsim_envs-2.10.9.dist-info/WHEEL
navsim_envs-2.10.9.dist-info/entry_points.txt
navsim_envs-2.10.9.dist-info/top_level.txt
navsim_envs-2.10.9.dist-info/RECORD
