Metadata-Version: 2.1
Name: navsim-envs
Version: 2.10.9
Summary: Navigation Simulator Environments
Home-page: UNKNOWN
Author: AF, STTC, IST, UCF
Author-email: armando@ucf.edu
License: UNKNOWN
Platform: UNKNOWN
Classifier: Programming Language :: Python :: 3
Classifier: License :: OSI Approved :: Apache Software License
Classifier: Operating System :: OS Independent
Classifier: Topic :: Scientific/Engineering
Classifier: Topic :: Scientific/Engineering :: Mathematics
Classifier: Topic :: Scientific/Engineering :: Artificial Intelligence
Classifier: Topic :: Software Development
Classifier: Topic :: Software Development :: Libraries
Classifier: Intended Audience :: Developers
Classifier: Intended Audience :: Education
Classifier: Intended Audience :: Science/Research
Requires-Python: >=3.8
Requires-Dist: numpy
Requires-Dist: pytest
Requires-Dist: click
Requires-Dist: gym (>=0.18.0)
Requires-Dist: navsim-mlagents-envs (==0.27.0)
Requires-Dist: gym-unity (==0.27.0)
